pupil_apriltags/bindings.py
pupil_apriltags/__init__.py
pupil_apriltags/lib/apriltag.dll
pupil_apriltags/lib/apriltag.lib
pupil_apriltags-1.0.4.post11.dist-info/DELVEWHEEL
pupil_apriltags-1.0.4.post11.dist-info/LICENSE
pupil_apriltags-1.0.4.post11.dist-info/METADATA
pupil_apriltags-1.0.4.post11.dist-info/RECORD
pupil_apriltags-1.0.4.post11.dist-info/top_level.txt
pupil_apriltags-1.0.4.post11.dist-info/WHEEL
pupil_apriltags.libs/.load-order-pupil_apriltags-1.0.4.post11
pupil_apriltags.libs/msvcr100.dll
pupil_apriltags.libs/pthreadVC2.dll
