Metadata-Version: 2.1
Name: pupil-apriltags
Version: 1.0.4.post11
Summary: Python bindings for apriltags v3
Home-page: https://github.com/pupil-labs/apriltags
Author: Pupil Labs GmbH
Author-email: info@pupil-labs.com
License: MIT
Project-URL: Documentation, https://pupil-apriltags.readthedocs.io/en/stable/
Project-URL: History, https://pupil-apriltags.readthedocs.io/en/latest/history.html
Classifier: Development Status :: 5 - Production/Stable
Classifier: Intended Audience :: Developers
Classifier: License :: OSI Approved :: MIT License
Classifier: Programming Language :: Python :: 3
Classifier: Programming Language :: Python :: 3 :: Only
Requires-Python: >=3.6
License-File: LICENSE
Requires-Dist: numpy
Requires-Dist: pupil-pthreads-win ; platform_system == "Windows" and python_version < "3.8"
Requires-Dist: importlib-metadata ; python_version < "3.8"
Provides-Extra: docs
Requires-Dist: furo ; extra == 'docs'
Requires-Dist: jaraco.packaging >=9 ; extra == 'docs'
Requires-Dist: rst.linker >=1.9 ; extra == 'docs'
Requires-Dist: sphinx ; extra == 'docs'
Provides-Extra: testing
Requires-Dist: pytest >=6 ; extra == 'testing'
Requires-Dist: pytest-checkdocs >=2.4 ; extra == 'testing'
Requires-Dist: pytest-cov ; extra == 'testing'
Requires-Dist: pytest-enabler >=1.3 ; extra == 'testing'
Requires-Dist: pytest-mypy >=0.9.1 ; (platform_python_implementation != "PyPy") and extra == 'testing'
